istar_m9csz_core/__init__.py
istar_m9csz_core/__main__.py
istar_m9csz_core/appdata.py
istar_m9csz_core/data.py
istar_m9csz_core/appdata/config.json
istar_m9csz_core/appdata/data_format.json
istar_m9csz_core/appdata/help_strings.json
istar_m9csz_core/structs/__init__.py
istar_m9csz_core/structs/avg_fns.py
istar_m9csz_core/structs/latlon.py
istar_m9csz_core/structs/realization.py
m9csz_core/__init__.py
m9csz_core/__main__.py
m9csz_core/appdata.py
m9csz_core/data.py
m9csz_core/structs/__init__.py
m9csz_core/structs/avg_fns.py
m9csz_core/structs/latlon.py
m9csz_core/structs/realization.py
structs/__init__.py
structs/avg_fns.py
structs/latlon.py
structs/realization.py
istar_m9csz_core-0.0.9.dist-info/LICENSE
istar_m9csz_core-0.0.9.dist-info/METADATA
istar_m9csz_core-0.0.9.dist-info/WHEEL
istar_m9csz_core-0.0.9.dist-info/top_level.txt
istar_m9csz_core-0.0.9.dist-info/RECORD
